{
    "item.neoncraft2.neon_tube": "霓虹灯管",
	"item.neoncraft2.glass_stick": "玻璃管",

	"block.neoncraft2.wallneon_letter_a_white": "字母 A 霓虹灯 - 白色",
	"block.neoncraft2.wallneon_letter_b_white": "字母 B 霓虹灯 - 白色",
	"block.neoncraft2.wallneon_letter_c_white": "字母 C 霓虹灯 - 白色",
	"block.neoncraft2.wallneon_letter_d_white": "字母 D 霓虹灯 - 白色",
	"block.neoncraft2.wallneon_letter_e_white": "字母 E 霓虹灯 - 白色",
	"block.neoncraft2.wallneon_letter_f_white": "字母 F 霓虹灯 - 白色",
	"block.neoncraft2.wallneon_letter_g_white": "字母 G 霓虹灯 - 白色",
	"block.neoncraft2.wallneon_letter_h_white": "字母 H 霓虹灯 - 白色",
	"block.neoncraft2.wallneon_letter_i_white": "字母 I 霓虹灯 - 白色",
	"block.neoncraft2.wallneon_letter_j_white": "字母 J 霓虹灯 - 白色",
	"block.neoncraft2.wallneon_letter_k_white": "字母 K 霓虹灯 - 白色",
	"block.neoncraft2.wallneon_letter_l_white": "字母 L 霓虹灯 - 白色",
	"block.neoncraft2.wallneon_letter_m_white": "字母 M 霓虹灯 - 白色",
	"block.neoncraft2.wallneon_letter_n_white": "字母 N 霓虹灯 - 白色",
	"block.neoncraft2.wallneon_letter_o_white": "字母 O 霓虹灯 - 白色",
	"block.neoncraft2.wallneon_letter_p_white": "字母 P 霓虹灯 - 白色",
	"block.neoncraft2.wallneon_letter_q_white": "字母 Q 霓虹灯 - 白色",
	"block.neoncraft2.wallneon_letter_r_white": "字母 R 霓虹灯 - 白色",
	"block.neoncraft2.wallneon_letter_s_white": "字母 S 霓虹灯 - 白色",
	"block.neoncraft2.wallneon_letter_t_white": "字母 T 霓虹灯 - 白色",
	"block.neoncraft2.wallneon_letter_u_white": "字母 U 霓虹灯 - 白色",
	"block.neoncraft2.wallneon_letter_v_white": "字母 V 霓虹灯 - 白色",
	"block.neoncraft2.wallneon_letter_w_white": "字母 W 霓虹灯 - 白色",
	"block.neoncraft2.wallneon_letter_x_white": "字母 X 霓虹灯 - 白色",
	"block.neoncraft2.wallneon_letter_y_white": "字母 Y 霓虹灯 - 白色",
	"block.neoncraft2.wallneon_letter_z_white": "字母 Z 霓虹灯 - 白色",
	"block.neoncraft2.wallneon_number_0_white": "数字 0 霓虹灯 - 白色",
	"block.neoncraft2.wallneon_number_1_white": "数字 1 霓虹灯 - 白色",
	"block.neoncraft2.wallneon_number_2_white": "数字 2 霓虹灯 - 白色",
	"block.neoncraft2.wallneon_number_3_white": "数字 3 霓虹灯 - 白色",
	"block.neoncraft2.wallneon_number_4_white": "数字 4 霓虹灯 - 白色",
	"block.neoncraft2.wallneon_number_5_white": "数字 5 霓虹灯 - 白色",
	"block.neoncraft2.wallneon_number_6_white": "数字 6 霓虹灯 - 白色",
	"block.neoncraft2.wallneon_number_7_white": "数字 7 霓虹灯 - 白色",
	"block.neoncraft2.wallneon_number_8_white": "数字 8 霓虹灯 - 白色",
	"block.neoncraft2.wallneon_number_9_white": "数字 9 霓虹灯 - 白色",
	"block.neoncraft2.wallneon_arrow_left_white": "左箭头霓虹灯 - 白色",
	"block.neoncraft2.wallneon_arrow_right_white": "右箭头霓虹灯 - 白色",
	"block.neoncraft2.wallneon_arrow_up_white": "上箭头霓虹灯 - 白色",
	"block.neoncraft2.wallneon_arrow_down_white": "下箭头霓虹灯 - 白色",

	"block.neoncraft2.wallneon_letter_a_red": "字母 A 霓虹灯 - 红色",
	"block.neoncraft2.wallneon_letter_b_red": "字母 B 霓虹灯 - 红色",
	"block.neoncraft2.wallneon_letter_c_red": "字母 C 霓虹灯 - 红色",
	"block.neoncraft2.wallneon_letter_d_red": "字母 D 霓虹灯 - 红色",
	"block.neoncraft2.wallneon_letter_e_red": "字母 E 霓虹灯 - 红色",
	"block.neoncraft2.wallneon_letter_f_red": "字母 F 霓虹灯 - 红色",
	"block.neoncraft2.wallneon_letter_g_red": "字母 G 霓虹灯 - 红色",
	"block.neoncraft2.wallneon_letter_h_red": "字母 H 霓虹灯 - 红色",
	"block.neoncraft2.wallneon_letter_i_red": "字母 I 霓虹灯 - 红色",
	"block.neoncraft2.wallneon_letter_j_red": "字母 J 霓虹灯 - 红色",
	"block.neoncraft2.wallneon_letter_k_red": "字母 K 霓虹灯 - 红色",
	"block.neoncraft2.wallneon_letter_l_red": "字母 L 霓虹灯 - 红色",
	"block.neoncraft2.wallneon_letter_m_red": "字母 M 霓虹灯 - 红色",
	"block.neoncraft2.wallneon_letter_n_red": "字母 N 霓虹灯 - 红色",
	"block.neoncraft2.wallneon_letter_o_red": "字母 O 霓虹灯 - 红色",
	"block.neoncraft2.wallneon_letter_p_red": "字母 P 霓虹灯 - 红色",
	"block.neoncraft2.wallneon_letter_q_red": "字母 Q 霓虹灯 - 红色",
	"block.neoncraft2.wallneon_letter_r_red": "字母 R 霓虹灯 - 红色",
	"block.neoncraft2.wallneon_letter_s_red": "字母 S 霓虹灯 - 红色",
	"block.neoncraft2.wallneon_letter_t_red": "字母 T 霓虹灯 - 红色",
	"block.neoncraft2.wallneon_letter_u_red": "字母 U 霓虹灯 - 红色",
	"block.neoncraft2.wallneon_letter_v_red": "字母 V 霓虹灯 - 红色",
	"block.neoncraft2.wallneon_letter_w_red": "字母 W 霓虹灯 - 红色",
	"block.neoncraft2.wallneon_letter_x_red": "字母 X 霓虹灯 - 红色",
	"block.neoncraft2.wallneon_letter_y_red": "字母 Y 霓虹灯 - 红色",
	"block.neoncraft2.wallneon_letter_z_red": "字母 Z 霓虹灯 - 红色",
	"block.neoncraft2.wallneon_number_0_red": "数字 0 霓虹灯 - 红色",
	"block.neoncraft2.wallneon_number_1_red": "数字 1 霓虹灯 - 红色",
	"block.neoncraft2.wallneon_number_2_red": "数字 2 霓虹灯 - 红色",
	"block.neoncraft2.wallneon_number_3_red": "数字 3 霓虹灯 - 红色",
	"block.neoncraft2.wallneon_number_4_red": "数字 4 霓虹灯 - 红色",
	"block.neoncraft2.wallneon_number_5_red": "数字 5 霓虹灯 - 红色",
	"block.neoncraft2.wallneon_number_6_red": "数字 6 霓虹灯 - 红色",
	"block.neoncraft2.wallneon_number_7_red": "数字 7 霓虹灯 - 红色",
	"block.neoncraft2.wallneon_number_8_red": "数字 8 霓虹灯 - 红色",
	"block.neoncraft2.wallneon_number_9_red": "数字 9 霓虹灯 - 红色",
	"block.neoncraft2.wallneon_arrow_left_red": "左箭头霓虹灯 - 红色",
	"block.neoncraft2.wallneon_arrow_right_red": "右箭头霓虹灯 - 红色",
	"block.neoncraft2.wallneon_arrow_up_red": "上箭头霓虹灯 - 红色",
	"block.neoncraft2.wallneon_arrow_down_red": "下箭头霓虹灯 - 红色",

	"block.neoncraft2.wallneon_letter_a_orange": "字母 A 霓虹灯 - 橙色",
	"block.neoncraft2.wallneon_letter_b_orange": "字母 B 霓虹灯 - 橙色",
	"block.neoncraft2.wallneon_letter_c_orange": "字母 C 霓虹灯 - 橙色",
	"block.neoncraft2.wallneon_letter_d_orange": "字母 D 霓虹灯 - 橙色",
	"block.neoncraft2.wallneon_letter_e_orange": "字母 E 霓虹灯 - 橙色",
	"block.neoncraft2.wallneon_letter_f_orange": "字母 F 霓虹灯 - 橙色",
	"block.neoncraft2.wallneon_letter_g_orange": "字母 G 霓虹灯 - 橙色",
	"block.neoncraft2.wallneon_letter_h_orange": "字母 H 霓虹灯 - 橙色",
	"block.neoncraft2.wallneon_letter_i_orange": "字母 I 霓虹灯 - 橙色",
	"block.neoncraft2.wallneon_letter_j_orange": "字母 J 霓虹灯 - 橙色",
	"block.neoncraft2.wallneon_letter_k_orange": "字母 K 霓虹灯 - 橙色",
	"block.neoncraft2.wallneon_letter_l_orange": "字母 L 霓虹灯 - 橙色",
	"block.neoncraft2.wallneon_letter_m_orange": "字母 M 霓虹灯 - 橙色",
	"block.neoncraft2.wallneon_letter_n_orange": "字母 N 霓虹灯 - 橙色",
	"block.neoncraft2.wallneon_letter_o_orange": "字母 O 霓虹灯 - 橙色",
	"block.neoncraft2.wallneon_letter_p_orange": "字母 P 霓虹灯 - 橙色",
	"block.neoncraft2.wallneon_letter_q_orange": "字母 Q 霓虹灯 - 橙色",
	"block.neoncraft2.wallneon_letter_r_orange": "字母 R 霓虹灯 - 橙色",
	"block.neoncraft2.wallneon_letter_s_orange": "字母 S 霓虹灯 - 橙色",
	"block.neoncraft2.wallneon_letter_t_orange": "字母 T 霓虹灯 - 橙色",
	"block.neoncraft2.wallneon_letter_u_orange": "字母 U 霓虹灯 - 橙色",
	"block.neoncraft2.wallneon_letter_v_orange": "字母 V 霓虹灯 - 橙色",
	"block.neoncraft2.wallneon_letter_w_orange": "字母 W 霓虹灯 - 橙色",
	"block.neoncraft2.wallneon_letter_x_orange": "字母 X 霓虹灯 - 橙色",
	"block.neoncraft2.wallneon_letter_y_orange": "字母 Y 霓虹灯 - 橙色",
	"block.neoncraft2.wallneon_letter_z_orange": "字母 Z 霓虹灯 - 橙色",
	"block.neoncraft2.wallneon_number_0_orange": "数字 0 霓虹灯 - 橙色",
	"block.neoncraft2.wallneon_number_1_orange": "数字 1 霓虹灯 - 橙色",
	"block.neoncraft2.wallneon_number_2_orange": "数字 2 霓虹灯 - 橙色",
	"block.neoncraft2.wallneon_number_3_orange": "数字 3 霓虹灯 - 橙色",
	"block.neoncraft2.wallneon_number_4_orange": "数字 4 霓虹灯 - 橙色",
	"block.neoncraft2.wallneon_number_5_orange": "数字 5 霓虹灯 - 橙色",
	"block.neoncraft2.wallneon_number_6_orange": "数字 6 霓虹灯 - 橙色",
	"block.neoncraft2.wallneon_number_7_orange": "数字 7 霓虹灯 - 橙色",
	"block.neoncraft2.wallneon_number_8_orange": "数字 8 霓虹灯 - 橙色",
	"block.neoncraft2.wallneon_number_9_orange": "数字 9 霓虹灯 - 橙色",
	"block.neoncraft2.wallneon_arrow_left_orange": "左箭头霓虹灯 - 橙色",
	"block.neoncraft2.wallneon_arrow_right_orange": "右箭头霓虹灯 - 橙色",
	"block.neoncraft2.wallneon_arrow_up_orange": "上箭头霓虹灯 - 橙色",
	"block.neoncraft2.wallneon_arrow_down_orange": "下箭头霓虹灯 - 橙色",

	"block.neoncraft2.wallneon_letter_a_yellow": "字母 A 霓虹灯 - 黄色",
	"block.neoncraft2.wallneon_letter_b_yellow": "字母 B 霓虹灯 - 黄色",
	"block.neoncraft2.wallneon_letter_c_yellow": "字母 C 霓虹灯 - 黄色",
	"block.neoncraft2.wallneon_letter_d_yellow": "字母 D 霓虹灯 - 黄色",
	"block.neoncraft2.wallneon_letter_e_yellow": "字母 E 霓虹灯 - 黄色",
	"block.neoncraft2.wallneon_letter_f_yellow": "字母 F 霓虹灯 - 黄色",
	"block.neoncraft2.wallneon_letter_g_yellow": "字母 G 霓虹灯 - 黄色",
	"block.neoncraft2.wallneon_letter_h_yellow": "字母 H 霓虹灯 - 黄色",
	"block.neoncraft2.wallneon_letter_i_yellow": "字母 I 霓虹灯 - 黄色",
	"block.neoncraft2.wallneon_letter_j_yellow": "字母 J 霓虹灯 - 黄色",
	"block.neoncraft2.wallneon_letter_k_yellow": "字母 K 霓虹灯 - 黄色",
	"block.neoncraft2.wallneon_letter_l_yellow": "字母 L 霓虹灯 - 黄色",
	"block.neoncraft2.wallneon_letter_m_yellow": "字母 M 霓虹灯 - 黄色",
	"block.neoncraft2.wallneon_letter_n_yellow": "字母 N 霓虹灯 - 黄色",
	"block.neoncraft2.wallneon_letter_o_yellow": "字母 O 霓虹灯 - 黄色",
	"block.neoncraft2.wallneon_letter_p_yellow": "字母 P 霓虹灯 - 黄色",
	"block.neoncraft2.wallneon_letter_q_yellow": "字母 Q 霓虹灯 - 黄色",
	"block.neoncraft2.wallneon_letter_r_yellow": "字母 R 霓虹灯 - 黄色",
	"block.neoncraft2.wallneon_letter_s_yellow": "字母 S 霓虹灯 - 黄色",
	"block.neoncraft2.wallneon_letter_t_yellow": "字母 T 霓虹灯 - 黄色",
	"block.neoncraft2.wallneon_letter_u_yellow": "字母 U 霓虹灯 - 黄色",
	"block.neoncraft2.wallneon_letter_v_yellow": "字母 V 霓虹灯 - 黄色",
	"block.neoncraft2.wallneon_letter_w_yellow": "字母 W 霓虹灯 - 黄色",
	"block.neoncraft2.wallneon_letter_x_yellow": "字母 X 霓虹灯 - 黄色",
	"block.neoncraft2.wallneon_letter_y_yellow": "字母 Y 霓虹灯 - 黄色",
	"block.neoncraft2.wallneon_letter_z_yellow": "字母 Z 霓虹灯 - 黄色",
	"block.neoncraft2.wallneon_number_0_yellow": "数字 0 霓虹灯 - 黄色",
	"block.neoncraft2.wallneon_number_1_yellow": "数字 1 霓虹灯 - 黄色",
	"block.neoncraft2.wallneon_number_2_yellow": "数字 2 霓虹灯 - 黄色",
	"block.neoncraft2.wallneon_number_3_yellow": "数字 3 霓虹灯 - 黄色",
	"block.neoncraft2.wallneon_number_4_yellow": "数字 4 霓虹灯 - 黄色",
	"block.neoncraft2.wallneon_number_5_yellow": "数字 5 霓虹灯 - 黄色",
	"block.neoncraft2.wallneon_number_6_yellow": "数字 6 霓虹灯 - 黄色",
	"block.neoncraft2.wallneon_number_7_yellow": "数字 7 霓虹灯 - 黄色",
	"block.neoncraft2.wallneon_number_8_yellow": "数字 8 霓虹灯 - 黄色",
	"block.neoncraft2.wallneon_number_9_yellow": "数字 9 霓虹灯 - 黄色",
	"block.neoncraft2.wallneon_arrow_left_yellow": "左箭头霓虹灯 - 黄色",
	"block.neoncraft2.wallneon_arrow_right_yellow": "右箭头霓虹灯 - 黄色",
	"block.neoncraft2.wallneon_arrow_up_yellow": "上箭头霓虹灯 - 黄色",
	"block.neoncraft2.wallneon_arrow_down_yellow": "下箭头霓虹灯 - 黄色",

	"block.neoncraft2.wallneon_letter_a_green": "字母 A 霓虹灯 - 绿色",
	"block.neoncraft2.wallneon_letter_b_green": "字母 B 霓虹灯 - 绿色",
	"block.neoncraft2.wallneon_letter_c_green": "字母 C 霓虹灯 - 绿色",
	"block.neoncraft2.wallneon_letter_d_green": "字母 D 霓虹灯 - 绿色",
	"block.neoncraft2.wallneon_letter_e_green": "字母 E 霓虹灯 - 绿色",
	"block.neoncraft2.wallneon_letter_f_green": "字母 F 霓虹灯 - 绿色",
	"block.neoncraft2.wallneon_letter_g_green": "字母 G 霓虹灯 - 绿色",
	"block.neoncraft2.wallneon_letter_h_green": "字母 H 霓虹灯 - 绿色",
	"block.neoncraft2.wallneon_letter_i_green": "字母 I 霓虹灯 - 绿色",
	"block.neoncraft2.wallneon_letter_j_green": "字母 J 霓虹灯 - 绿色",
	"block.neoncraft2.wallneon_letter_k_green": "字母 K 霓虹灯 - 绿色",
	"block.neoncraft2.wallneon_letter_l_green": "字母 L 霓虹灯 - 绿色",
	"block.neoncraft2.wallneon_letter_m_green": "字母 M 霓虹灯 - 绿色",
	"block.neoncraft2.wallneon_letter_n_green": "字母 N 霓虹灯 - 绿色",
	"block.neoncraft2.wallneon_letter_o_green": "字母 O 霓虹灯 - 绿色",
	"block.neoncraft2.wallneon_letter_p_green": "字母 P 霓虹灯 - 绿色",
	"block.neoncraft2.wallneon_letter_q_green": "字母 Q 霓虹灯 - 绿色",
	"block.neoncraft2.wallneon_letter_r_green": "字母 R 霓虹灯 - 绿色",
	"block.neoncraft2.wallneon_letter_s_green": "字母 S 霓虹灯 - 绿色",
	"block.neoncraft2.wallneon_letter_t_green": "字母 T 霓虹灯 - 绿色",
	"block.neoncraft2.wallneon_letter_u_green": "字母 U 霓虹灯 - 绿色",
	"block.neoncraft2.wallneon_letter_v_green": "字母 V 霓虹灯 - 绿色",
	"block.neoncraft2.wallneon_letter_w_green": "字母 W 霓虹灯 - 绿色",
	"block.neoncraft2.wallneon_letter_x_green": "字母 X 霓虹灯 - 绿色",
	"block.neoncraft2.wallneon_letter_y_green": "字母 Y 霓虹灯 - 绿色",
	"block.neoncraft2.wallneon_letter_z_green": "字母 Z 霓虹灯 - 绿色",
	"block.neoncraft2.wallneon_number_0_green": "数字 0 霓虹灯 - 绿色",
	"block.neoncraft2.wallneon_number_1_green": "数字 1 霓虹灯 - 绿色",
	"block.neoncraft2.wallneon_number_2_green": "数字 2 霓虹灯 - 绿色",
	"block.neoncraft2.wallneon_number_3_green": "数字 3 霓虹灯 - 绿色",
	"block.neoncraft2.wallneon_number_4_green": "数字 4 霓虹灯 - 绿色",
	"block.neoncraft2.wallneon_number_5_green": "数字 5 霓虹灯 - 绿色",
	"block.neoncraft2.wallneon_number_6_green": "数字 6 霓虹灯 - 绿色",
	"block.neoncraft2.wallneon_number_7_green": "数字 7 霓虹灯 - 绿色",
	"block.neoncraft2.wallneon_number_8_green": "数字 8 霓虹灯 - 绿色",
	"block.neoncraft2.wallneon_number_9_green": "数字 9 霓虹灯 - 绿色",
	"block.neoncraft2.wallneon_arrow_left_green": "左箭头霓虹灯 - 绿色",
	"block.neoncraft2.wallneon_arrow_right_green": "右箭头霓虹灯 - 绿色",
	"block.neoncraft2.wallneon_arrow_up_green": "上箭头霓虹灯 - 绿色",
	"block.neoncraft2.wallneon_arrow_down_green": "下箭头霓虹灯 - 绿色",

	"block.neoncraft2.wallneon_letter_a_blue": "字母 A 霓虹灯 - 蓝色",
	"block.neoncraft2.wallneon_letter_b_blue": "字母 B 霓虹灯 - 蓝色",
	"block.neoncraft2.wallneon_letter_c_blue": "字母 C 霓虹灯 - 蓝色",
	"block.neoncraft2.wallneon_letter_d_blue": "字母 D 霓虹灯 - 蓝色",
	"block.neoncraft2.wallneon_letter_e_blue": "字母 E 霓虹灯 - 蓝色",
	"block.neoncraft2.wallneon_letter_f_blue": "字母 F 霓虹灯 - 蓝色",
	"block.neoncraft2.wallneon_letter_g_blue": "字母 G 霓虹灯 - 蓝色",
	"block.neoncraft2.wallneon_letter_h_blue": "字母 H 霓虹灯 - 蓝色",
	"block.neoncraft2.wallneon_letter_i_blue": "字母 I 霓虹灯 - 蓝色",
	"block.neoncraft2.wallneon_letter_j_blue": "字母 J 霓虹灯 - 蓝色",
	"block.neoncraft2.wallneon_letter_k_blue": "字母 K 霓虹灯 - 蓝色",
	"block.neoncraft2.wallneon_letter_l_blue": "字母 L 霓虹灯 - 蓝色",
	"block.neoncraft2.wallneon_letter_m_blue": "字母 M 霓虹灯 - 蓝色",
	"block.neoncraft2.wallneon_letter_n_blue": "字母 N 霓虹灯 - 蓝色",
	"block.neoncraft2.wallneon_letter_o_blue": "字母 O 霓虹灯 - 蓝色",
	"block.neoncraft2.wallneon_letter_p_blue": "字母 P 霓虹灯 - 蓝色",
	"block.neoncraft2.wallneon_letter_q_blue": "字母 Q 霓虹灯 - 蓝色",
	"block.neoncraft2.wallneon_letter_r_blue": "字母 R 霓虹灯 - 蓝色",
	"block.neoncraft2.wallneon_letter_s_blue": "字母 S 霓虹灯 - 蓝色",
	"block.neoncraft2.wallneon_letter_t_blue": "字母 T 霓虹灯 - 蓝色",
	"block.neoncraft2.wallneon_letter_u_blue": "字母 U 霓虹灯 - 蓝色",
	"block.neoncraft2.wallneon_letter_v_blue": "字母 V 霓虹灯 - 蓝色",
	"block.neoncraft2.wallneon_letter_w_blue": "字母 W 霓虹灯 - 蓝色",
	"block.neoncraft2.wallneon_letter_x_blue": "字母 X 霓虹灯 - 蓝色",
	"block.neoncraft2.wallneon_letter_y_blue": "字母 Y 霓虹灯 - 蓝色",
	"block.neoncraft2.wallneon_letter_z_blue": "字母 Z 霓虹灯 - 蓝色",
	"block.neoncraft2.wallneon_number_0_blue": "数字 0 霓虹灯 - 蓝色",
	"block.neoncraft2.wallneon_number_1_blue": "数字 1 霓虹灯 - 蓝色",
	"block.neoncraft2.wallneon_number_2_blue": "数字 2 霓虹灯 - 蓝色",
	"block.neoncraft2.wallneon_number_3_blue": "数字 3 霓虹灯 - 蓝色",
	"block.neoncraft2.wallneon_number_4_blue": "数字 4 霓虹灯 - 蓝色",
	"block.neoncraft2.wallneon_number_5_blue": "数字 5 霓虹灯 - 蓝色",
	"block.neoncraft2.wallneon_number_6_blue": "数字 6 霓虹灯 - 蓝色",
	"block.neoncraft2.wallneon_number_7_blue": "数字 7 霓虹灯 - 蓝色",
	"block.neoncraft2.wallneon_number_8_blue": "数字 8 霓虹灯 - 蓝色",
	"block.neoncraft2.wallneon_number_9_blue": "数字 9 霓虹灯 - 蓝色",
	"block.neoncraft2.wallneon_arrow_left_blue": "左箭头霓虹灯 - 蓝色",
	"block.neoncraft2.wallneon_arrow_right_blue": "右箭头霓虹灯 - 蓝色",
	"block.neoncraft2.wallneon_arrow_up_blue": "上箭头霓虹灯 - 蓝色",
	"block.neoncraft2.wallneon_arrow_down_blue": "下箭头霓虹灯 - 蓝色",

	"block.neoncraft2.wallneon_letter_a_purple": "字母 A 霓虹灯 - 紫色",
	"block.neoncraft2.wallneon_letter_b_purple": "字母 B 霓虹灯 - 紫色",
	"block.neoncraft2.wallneon_letter_c_purple": "字母 C 霓虹灯 - 紫色",
	"block.neoncraft2.wallneon_letter_d_purple": "字母 D 霓虹灯 - 紫色",
	"block.neoncraft2.wallneon_letter_e_purple": "字母 E 霓虹灯 - 紫色",
	"block.neoncraft2.wallneon_letter_f_purple": "字母 F 霓虹灯 - 紫色",
	"block.neoncraft2.wallneon_letter_g_purple": "字母 G 霓虹灯 - 紫色",
	"block.neoncraft2.wallneon_letter_h_purple": "字母 H 霓虹灯 - 紫色",
	"block.neoncraft2.wallneon_letter_i_purple": "字母 I 霓虹灯 - 紫色",
	"block.neoncraft2.wallneon_letter_j_purple": "字母 J 霓虹灯 - 紫色",
	"block.neoncraft2.wallneon_letter_k_purple": "字母 K 霓虹灯 - 紫色",
	"block.neoncraft2.wallneon_letter_l_purple": "字母 L 霓虹灯 - 紫色",
	"block.neoncraft2.wallneon_letter_m_purple": "字母 M 霓虹灯 - 紫色",
	"block.neoncraft2.wallneon_letter_n_purple": "字母 N 霓虹灯 - 紫色",
	"block.neoncraft2.wallneon_letter_o_purple": "字母 O 霓虹灯 - 紫色",
	"block.neoncraft2.wallneon_letter_p_purple": "字母 P 霓虹灯 - 紫色",
	"block.neoncraft2.wallneon_letter_q_purple": "字母 Q 霓虹灯 - 紫色",
	"block.neoncraft2.wallneon_letter_r_purple": "字母 R 霓虹灯 - 紫色",
	"block.neoncraft2.wallneon_letter_s_purple": "字母 S 霓虹灯 - 紫色",
	"block.neoncraft2.wallneon_letter_t_purple": "字母 T 霓虹灯 - 紫色",
	"block.neoncraft2.wallneon_letter_u_purple": "字母 U 霓虹灯 - 紫色",
	"block.neoncraft2.wallneon_letter_v_purple": "字母 V 霓虹灯 - 紫色",
	"block.neoncraft2.wallneon_letter_w_purple": "字母 W 霓虹灯 - 紫色",
	"block.neoncraft2.wallneon_letter_x_purple": "字母 X 霓虹灯 - 紫色",
	"block.neoncraft2.wallneon_letter_y_purple": "字母 Y 霓虹灯 - 紫色",
	"block.neoncraft2.wallneon_letter_z_purple": "字母 Z 霓虹灯 - 紫色",
	"block.neoncraft2.wallneon_number_0_purple": "数字 0 霓虹灯 - 紫色",
	"block.neoncraft2.wallneon_number_1_purple": "数字 1 霓虹灯 - 紫色",
	"block.neoncraft2.wallneon_number_2_purple": "数字 2 霓虹灯 - 紫色",
	"block.neoncraft2.wallneon_number_3_purple": "数字 3 霓虹灯 - 紫色",
	"block.neoncraft2.wallneon_number_4_purple": "数字 4 霓虹灯 - 紫色",
	"block.neoncraft2.wallneon_number_5_purple": "数字 5 霓虹灯 - 紫色",
	"block.neoncraft2.wallneon_number_6_purple": "数字 6 霓虹灯 - 紫色",
	"block.neoncraft2.wallneon_number_7_purple": "数字 7 霓虹灯 - 紫色",
	"block.neoncraft2.wallneon_number_8_purple": "数字 8 霓虹灯 - 紫色",
	"block.neoncraft2.wallneon_number_9_purple": "数字 9 霓虹灯 - 紫色",
	"block.neoncraft2.wallneon_arrow_left_purple": "左箭头霓虹灯 - 紫色",
	"block.neoncraft2.wallneon_arrow_right_purple": "右箭头霓虹灯 - 紫色",
	"block.neoncraft2.wallneon_arrow_up_purple": "上箭头霓虹灯 - 紫色",
	"block.neoncraft2.wallneon_arrow_down_purple": "下箭头霓虹灯 - 紫色",

	"block.neoncraft2.wallneon_letter_a_pink": "字母 A 霓虹灯 - 粉色",
	"block.neoncraft2.wallneon_letter_b_pink": "字母 B 霓虹灯 - 粉色",
	"block.neoncraft2.wallneon_letter_c_pink": "字母 C 霓虹灯 - 粉色",
	"block.neoncraft2.wallneon_letter_d_pink": "字母 D 霓虹灯 - 粉色",
	"block.neoncraft2.wallneon_letter_e_pink": "字母 E 霓虹灯 - 粉色",
	"block.neoncraft2.wallneon_letter_f_pink": "字母 F 霓虹灯 - 粉色",
	"block.neoncraft2.wallneon_letter_g_pink": "字母 G 霓虹灯 - 粉色",
	"block.neoncraft2.wallneon_letter_h_pink": "字母 H 霓虹灯 - 粉色",
	"block.neoncraft2.wallneon_letter_i_pink": "字母 I 霓虹灯 - 粉色",
	"block.neoncraft2.wallneon_letter_j_pink": "字母 J 霓虹灯 - 粉色",
	"block.neoncraft2.wallneon_letter_k_pink": "字母 K 霓虹灯 - 粉色",
	"block.neoncraft2.wallneon_letter_l_pink": "字母 L 霓虹灯 - 粉色",
	"block.neoncraft2.wallneon_letter_m_pink": "字母 M 霓虹灯 - 粉色",
	"block.neoncraft2.wallneon_letter_n_pink": "字母 N 霓虹灯 - 粉色",
	"block.neoncraft2.wallneon_letter_o_pink": "字母 O 霓虹灯 - 粉色",
	"block.neoncraft2.wallneon_letter_p_pink": "字母 P 霓虹灯 - 粉色",
	"block.neoncraft2.wallneon_letter_q_pink": "字母 Q 霓虹灯 - 粉色",
	"block.neoncraft2.wallneon_letter_r_pink": "字母 R 霓虹灯 - 粉色",
	"block.neoncraft2.wallneon_letter_s_pink": "字母 S 霓虹灯 - 粉色",
	"block.neoncraft2.wallneon_letter_t_pink": "字母 T 霓虹灯 - 粉色",
	"block.neoncraft2.wallneon_letter_u_pink": "字母 U 霓虹灯 - 粉色",
	"block.neoncraft2.wallneon_letter_v_pink": "字母 V 霓虹灯 - 粉色",
	"block.neoncraft2.wallneon_letter_w_pink": "字母 W 霓虹灯 - 粉色",
	"block.neoncraft2.wallneon_letter_x_pink": "字母 X 霓虹灯 - 粉色",
	"block.neoncraft2.wallneon_letter_y_pink": "字母 Y 霓虹灯 - 粉色",
	"block.neoncraft2.wallneon_letter_z_pink": "字母 Z 霓虹灯 - 粉色",
	"block.neoncraft2.wallneon_number_0_pink": "数字 0 霓虹灯 - 粉色",
	"block.neoncraft2.wallneon_number_1_pink": "数字 1 霓虹灯 - 粉色",
	"block.neoncraft2.wallneon_number_2_pink": "数字 2 霓虹灯 - 粉色",
	"block.neoncraft2.wallneon_number_3_pink": "数字 3 霓虹灯 - 粉色",
	"block.neoncraft2.wallneon_number_4_pink": "数字 4 霓虹灯 - 粉色",
	"block.neoncraft2.wallneon_number_5_pink": "数字 5 霓虹灯 - 粉色",
	"block.neoncraft2.wallneon_number_6_pink": "数字 6 霓虹灯 - 粉色",
	"block.neoncraft2.wallneon_number_7_pink": "数字 7 霓虹灯 - 粉色",
	"block.neoncraft2.wallneon_number_8_pink": "数字 8 霓虹灯 - 粉色",
	"block.neoncraft2.wallneon_number_9_pink": "数字 9 霓虹灯 - 粉色",
	"block.neoncraft2.wallneon_arrow_left_pink": "左箭头霓虹灯 - 粉色",
	"block.neoncraft2.wallneon_arrow_right_pink": "右箭头霓虹灯 - 粉色",
	"block.neoncraft2.wallneon_arrow_up_pink": "上箭头霓虹灯 - 粉色",
	"block.neoncraft2.wallneon_arrow_down_pink": "下箭头霓虹灯 - 粉色",

	"itemGroup.neoncraft2": "霓虹灯艺 2"
}